{
"type": "FeatureCollection",
"name": "tulsa_bubble_federal_house_districts",
"crs": { "type": "name", "properties": { "name": "urn:ogc:def:crs:EPSG::4269" } },
"features": [
{ "type": "Feature", "properties": { "id": "4001", "name": "Congressional District 1", "pop": 646403.5222, "rhh": 104065.475 }, "geometry": { "type": "Point", "coordinates": [ -96.029776901740249, 36.14383 ] } }
]
}
